{
  "siteTitle": "Reset at 30",
  "siteDescription": "A thoughtful collection of stories about life, style, and everything in between.",
  "author": "Sukhman Kaur",
  "authorBio": "Welcome to my corner of the internet, where I share stories about life, style, travel, and everything that sparks joy.",
  "authorImage": {
    "src": "/uploads/360_F_155049786_Ch17gRfPjmKG5N9S21VMs8LWBkjkfVDi.jpg"
  },
  "socialLinks": {
    "email": "abc@abc.com",
    "twitter": "http://twitter.com/x",
    "instagram": "http://instagram.com/",
    "website": "https://resetat30.pages.dev/"
  }
}